schemapy/__init__.py
schemapy/action.py
schemapy/api.py
schemapy/exceptions.py
schemapy/response.py
schemapy/validators.py
schemapy-0.2.4.dist-info/DESCRIPTION.rst
schemapy-0.2.4.dist-info/METADATA
schemapy-0.2.4.dist-info/RECORD
schemapy-0.2.4.dist-info/WHEEL
schemapy-0.2.4.dist-info/metadata.json
schemapy-0.2.4.dist-info/top_level.txt
tests/__init__.py
tests/conftest.py
tests/test_action.py
tests/test_api.py
tests/test_response.py
tests/test_validators.py
