Metadata-Version: 2.0
Name: schemapy
Version: 0.2.4
Summary: Centralize database access
Home-page: https://github.com/link-society/schemapy
Author: Link Society
Author-email: contact@link-society.com
License: Apache
Keywords: schema api database
Platform: UNKNOWN
Classifier: Development Status :: 3 - Alpha
Classifier: Operating System :: OS Independent
Classifier: Programming Language :: Python
Classifier: Programming Language :: Python :: 3
Classifier: Programming Language :: Python :: 3.4
Classifier: Programming Language :: Python :: 3.5
Classifier: Programming Language :: Python :: 3.6
Classifier: Programming Language :: Python :: Implementation :: CPython
Requires-Dist: addict (>=2.1.2)
Requires-Dist: pyDAL (>=17.11)
Requires-Dist: pytest-runner (>=3.0)
